{
  "id": 47115,
  "university": {
    "fullName": "University of California San Diego",
    "shortName": "UC San Diego",
    "region": "North America",
    "hashTag": "#ucsd",
    "url": "http://www.ucsd.edu",
    "appYears": [
      2000,
      2001,
      2002,
      2003,
      2005,
      2009,
      2011
    ],
    "winYears": [],
    "goldYears": [],
    "silverYears": [],
    "bronzeYears": [],
    "regYears": []
  },
  "team": {
    "name": "UCSD Fallen Star",
    "regionals": [
      "North America, 5th"
    ]
  },
  "coach": {
    "name": "Zihan Wang",
    "altNames": [],
    "cfHandle": "Suzukaze",
    "cfRating": 2330,
    "twitterHandle": null,
    "achievements": [
      {
        "achievement": "ICPC WF Bronze Medalist (2020)",
        "priority": 102
      },
      {
        "achievement": "GHC Finalist (2022)",
        "priority": 70
      },
      {
        "achievement": "Forethought Future Cup Finalist (2019)",
        "priority": -10
      }
    ]
  },
  "contestants": [
    {
      "name": "Stanisław Strzelecki",
      "altNames": [],
      "cfHandle": "stasio6",
      "cfRating": 2593,
      "twitterHandle": null,
      "achievements": [
        {
          "achievement": "IOI Silver Medalist (2017)",
          "priority": 63
        }
      ]
    },
    {
      "name": "Shang Zhou",
      "altNames": [],
      "cfHandle": "ZhouShang0817",
      "cfRating": 2490,
      "twitterHandle": null,
      "achievements": []
    },
    {
      "name": "Thomas Li",
      "altNames": [],
      "cfHandle": "bitset",
      "cfRating": 2106,
      "twitterHandle": null,
      "achievements": []
    }
  ]
}